hrml/__init__.py
hrml/__main__.py
hrml/編譯工具.py
hrml-1.0.2.dist-info/METADATA
hrml-1.0.2.dist-info/WHEEL
hrml-1.0.2.dist-info/top_level.txt
hrml-1.0.2.dist-info/RECORD
