Metadata-Version: 2.1
Name: hrml
Version: 1.0.2
Summary: hrml
Home-page: https://github.com/RimoChan/hrml
Author: RimoChan
Author-email: the@librian.net
License: UNKNOWN
Platform: UNKNOWN
Classifier: Programming Language :: Python :: 3
Classifier: Operating System :: OS Independent
Requires-Python: >=3.5
Requires-Dist: fire (>=0.3.1)
